electricitycostcalculator/__init__.py
electricitycostcalculator/cost_calculator/.gitignore
electricitycostcalculator/cost_calculator/__init__.py
electricitycostcalculator/cost_calculator/cost_calculator.py
electricitycostcalculator/cost_calculator/rate_structure.py
electricitycostcalculator/cost_calculator/tariff_structure.py
electricitycostcalculator/oadr_signal/.gitignore
electricitycostcalculator/oadr_signal/DR_template.py
electricitycostcalculator/oadr_signal/__init__.py
electricitycostcalculator/oadr_signal/getDRSignal.py
electricitycostcalculator/oadr_signal/getPelicanDREvents.py
electricitycostcalculator/oadr_signal/getSCEEvents.py
electricitycostcalculator/oadr_signal/settings_template.json
electricitycostcalculator/oadr_signal/tariff_maps.py
electricitycostcalculator/oadr_signal/utils.py
electricitycostcalculator/openei_tariff/.gitignore
electricitycostcalculator/openei_tariff/E-190-revised.json
electricitycostcalculator/openei_tariff/PDP_events_ex.json
electricitycostcalculator/openei_tariff/__init__.py
electricitycostcalculator/openei_tariff/openei_tariff_analyzer.py
electricitycostcalculator/openei_tariff/u14328_Commercial_A-1 Small General Service_TOU_phaseSingle.json
electricitycostcalculator/openei_tariff/u14328_Commercial_A-1 Small General Service_TOU_phaseSingle_revised.json
electricitycostcalculator/openei_tariff/u14328_Commercial_A-10_TOU_gridlevelSecondary.json
electricitycostcalculator/openei_tariff/u14328_Commercial_A-10_TOU_gridlevelSecondary_revised.json
electricitycostcalculator/openei_tariff/u14328_Commercial_A-6_TOU.json
electricitycostcalculator/openei_tariff/u14328_Commercial_A-6_TOU_revised.json
electricitycostcalculator/openei_tariff/u14328_Commercial_B-19S_TOU_gridlevelSecondary_revised.json
electricitycostcalculator/openei_tariff/u14328_Commercial_B-19_TOU_gridlevelSecondary_revised.json
electricitycostcalculator/openei_tariff/u14328_Commercial_E-19_GENERATIONCREDIT_TOU_gridlevelSecondary_revised.json
electricitycostcalculator-0.2.2.dist-info/WHEEL
electricitycostcalculator-0.2.2.dist-info/METADATA
electricitycostcalculator-0.2.2.dist-info/RECORD
