Metadata-Version: 2.1
Name: electricitycostcalculator
Version: 0.2.2
Summary: 
Author: Olivier Van Cutsem
Requires-Python: >=3.6,<4.0
Classifier: Programming Language :: Python :: 3
Classifier: Programming Language :: Python :: 3.6
Classifier: Programming Language :: Python :: 3.7
Classifier: Programming Language :: Python :: 3.8
Requires-Dist: holidays (>=0.9.10,<0.10.0)
Requires-Dist: lxml (>=4.3,<5.0)
Requires-Dist: matplotlib (>=3.0,<4.0)
Requires-Dist: pandas (>=0.24.2,<0.25.0)
Requires-Dist: pytz (>=2019.1,<2020.0)
Requires-Dist: requests (>=2.21,<3.0)
